{"_path":"/projects/test-21","_dir":"projects","_draft":false,"_partial":false,"_locale":"","title":"Nieuw Artikel","description":"","slug":"test-21","category":"Website design","primaryImage":"/content/images/portfolio-item-1.jpg","body":{"type":"root","children":[{"type":"element","tag":"project-summary","props":{":client":"{\"label\":\"Wessel Oud\",\"image\":\"/content/images/portfolio-item-1.jpg\"}",":roles":"[\"Test rol\",\"Designer\"]"},"children":[{"type":"element","tag":"p","props":{},"children":[{"type":"text","value":"Ever since I completed my internship this fall, I've been eager to revamp my porfolio."}]},{"type":"element","tag":"p","props":{},"children":[{"type":"text","value":"I'm going for a dark theme this time and incorporating more"}]}]}],"toc":{"title":"","searchDepth":2,"depth":2,"links":[]}},"_type":"markdown","_id":"content:projects:test-21.md","_source":"content","_file":"projects/test-21.md","_extension":"md"}